explainaboard_cli/__init__.py
explainaboard_cli/__main__.py
explainaboard_cli/client.py
explainaboard_cli/config.py
explainaboard_cli/utils.py
explainaboard_cli/tests/__init__.py
explainaboard_cli/tests/test_info.py
explainaboard_cli/tests/test_system.py
explainaboard_cli/tests/test_user.py
explainaboard_cli/tests/test_utils.py
explainaboard_cli-0.0.2.dist-info/METADATA
explainaboard_cli-0.0.2.dist-info/WHEEL
explainaboard_cli-0.0.2.dist-info/entry_points.txt
explainaboard_cli-0.0.2.dist-info/top_level.txt
explainaboard_cli-0.0.2.dist-info/RECORD
