Metadata-Version: 2.1
Name: explainaboard-cli
Version: 0.0.2
Summary: Explainable CLI
Home-page: https://github.com/neulab/explainaboard_cli
License: MIT License
Platform: UNKNOWN
Classifier: Intended Audience :: Developers
Classifier: Topic :: Text Processing
Classifier: Topic :: Scientific/Engineering :: Artificial Intelligence
Classifier: License :: OSI Approved :: MIT License
Classifier: Programming Language :: Python :: 3.9
Classifier: Programming Language :: Python :: 3.10
Classifier: Programming Language :: Python :: 3 :: Only
Requires-Dist: explainaboard-api-client
Provides-Extra: dev
Requires-Dist: pre-commit ; extra == 'dev'
